curated_transformers/__init__.py
curated_transformers/_compat.py
curated_transformers/semver.py
curated_transformers/generation/__init__.py
curated_transformers/generation/auto_generator.py
curated_transformers/generation/config.py
curated_transformers/generation/default_generator.py
curated_transformers/generation/dolly_v2.py
curated_transformers/generation/falcon.py
curated_transformers/generation/generator.py
curated_transformers/generation/generator_wrapper.py
curated_transformers/generation/hf_hub.py
curated_transformers/generation/llama.py
curated_transformers/generation/logits.py
curated_transformers/generation/mpt.py
curated_transformers/generation/state.py
curated_transformers/generation/stop_conditions.py
curated_transformers/generation/string_generator.py
curated_transformers/layers/__init__.py
curated_transformers/layers/activations.py
curated_transformers/layers/attention.py
curated_transformers/layers/cache.py
curated_transformers/layers/embeddings.py
curated_transformers/layers/feedforward.py
curated_transformers/layers/normalization.py
curated_transformers/layers/transformer.py
curated_transformers/models/__init__.py
curated_transformers/models/auto_model.py
curated_transformers/models/config.py
curated_transformers/models/module.py
curated_transformers/models/output.py
curated_transformers/models/transformer.py
curated_transformers/models/albert/__init__.py
curated_transformers/models/albert/_hf.py
curated_transformers/models/albert/config.py
curated_transformers/models/albert/encoder.py
curated_transformers/models/albert/layer_group.py
curated_transformers/models/bert/__init__.py
curated_transformers/models/bert/_hf.py
curated_transformers/models/bert/config.py
curated_transformers/models/bert/encoder.py
curated_transformers/models/camembert/__init__.py
curated_transformers/models/camembert/_hf.py
curated_transformers/models/camembert/encoder.py
curated_transformers/models/electra/__init__.py
curated_transformers/models/electra/_hf.py
curated_transformers-2.0.0.dist-info/LICENSE
curated_transformers-2.0.0.dist-info/METADATA
curated_transformers-2.0.0.dist-info/WHEEL
curated_transformers-2.0.0.dist-info/entry_points.txt
curated_transformers-2.0.0.dist-info/top_level.txt
curated_transformers-2.0.0.dist-info/zip-safe
curated_transformers-2.0.0.dist-info/RECORD
