Metadata-Version: 2.1
Name: curated-transformers
Version: 2.0.0
Summary: A PyTorch library of transformer models and components
Home-page: https://github.com/explosion/curated-transformers
Author: Explosion
Author-email: contact@explosion.ai
License: MIT
Requires-Python: >=3.9
License-File: LICENSE
Requires-Dist: catalogue <2.1.0,>=2.0.4
Requires-Dist: curated-tokenizers <3.0.0,>=2.0.0
Requires-Dist: huggingface-hub >=0.14
Requires-Dist: tokenizers >=0.13.3
Requires-Dist: torch >=1.12.0
Provides-Extra: quantization
Requires-Dist: bitsandbytes >=0.40 ; extra == 'quantization'
Requires-Dist: scipy >=1.11 ; extra == 'quantization'
